{
    "name": "hxdispatch",
    "url" : "https://github.com/MaddinXx/hxdispatch",
    "license": "MIT",
    "tags": ["dispatch", "promise", "future", "async", "threaded", "event", "signal"],
    "description": "An optionally asynchronous dispatch library.",
    "classPath": "src",
    "dependencies": {
        "hxstd": ""
    },
    "version": "2.0.1",
    "releasenote": "Fix incompatible fn override; Executor as interface (nice with hxAnonCls)",
    "contributors": [
        "MaddinXx"
    ]
}
